reposlayer/__init__.py
reposlayer/cli.py
reposlayer/commands.py
reposlayer/counter/__init__.py
reposlayer/counter/counter.py
reposlayer-0.1.4.dist-info/LICENSE
reposlayer-0.1.4.dist-info/METADATA
reposlayer-0.1.4.dist-info/WHEEL
reposlayer-0.1.4.dist-info/entry_points.txt
reposlayer-0.1.4.dist-info/top_level.txt
reposlayer-0.1.4.dist-info/RECORD
