Metadata-Version: 2.2
Name: reposlayer
Version: 0.1.4
Summary: Python repository manager
Author-email: Richard Qu <rq2014@nyu.edu>
Maintainer-email: Richard Qu <rq2014@nyu.edu>
Keywords: python,repository,manager
Classifier: Development Status :: 3 - Alpha
Classifier: Programming Language :: Python :: 3
Classifier: License :: OSI Approved :: MIT License
Classifier: Operating System :: OS Independent
Requires-Python: >=3.6
License-File: LICENSE
Requires-Dist: pathlib
